unityneuro/__init__.py
unityneuro/ibl.py
unityneuro/render.py
unityneuro-0.4.4.dist-info/LICENSE
unityneuro-0.4.4.dist-info/METADATA
unityneuro-0.4.4.dist-info/WHEEL
unityneuro-0.4.4.dist-info/top_level.txt
unityneuro-0.4.4.dist-info/RECORD
