Metadata-Version: 2.1
Name: unityneuro
Version: 0.4.4
Summary: Urchin - Unity Renderer for Neuroscience Python API
Author-email: Daniel Birman <danbirman@gmail.com>
License: GNU GENERAL PUBLIC LICENSE
Project-URL: Homepage, https://virtualbrainlab.org/03_unity_neuro/01_urn_intro.html
Project-URL: Bug Tracker, https://github.com/VirtualBrainLab/UnityNeuroscience/issues
Classifier: Programming Language :: Python :: 3
Classifier: License :: OSI Approved :: MIT License
Classifier: Operating System :: OS Independent
Requires-Python: >=3.7
License-File: LICENSE
Requires-Dist: python-socketio[client]
Requires-Dist: numpy
